[
  {
    "label": "All (49)",
    "name": "all",
    "options": [
      {
        "label": "Undergraduate (7)",
        "name": "undergrad",
        "options": [
          {
            "label": "Bachelor (6)",
            "name": "bachelor",
            "isChecked": true
          },
          {
            "label": "Diploma (1)",
            "name": "diploma",
            "isChecked": true
          },
          {
            "label": "Honours (0)",
            "name": "honours",
            "isChecked": true
          }
        ]
      },
      {
        "label": "Graduate (38)",
        "name": "postgrad",
        "options": [
          {
            "label": "Certificate (10)",
            "name": "certificate",
            "isChecked": true
          },
          {
            "label": "Diploma (6)",
            "name": "diploma",
            "isChecked": true
          },
          {
            "label": "Master (22)",
            "name": "master",
            "isChecked": true
          }
        ]
      },
      {
        "label": "Research (4)",
        "name": "research",
        "options": [
          {
            "label": "Master (2)",
            "name": "master",
            "isChecked": true
          },
          {
            "label": "PhD (2)",
            "name": "phd",
            "isChecked": true
          }
        ]
      }
    ]
  }
]
